cdd_gae/__init__.py
cdd_gae/__main__.py
cdd_gae/ndb2sqlalchemy_migrator.py
cdd_gae/ndb2sqlalchemy_utils.py
cdd_gae/ndb_sqlalchemy_migrator_utils.py
cdd_gae/parquet_to_table.py
cdd_gae/webapp2_to_fastapi.py
cdd_gae/webapp2_to_fastapi_utils.py
cdd_gae/parse/__init__.py
cdd_gae/parse/ndb.py
cdd_gae/parse/ndb_utils.py
cdd_gae/parse/parquet.py
cdd_gae/parse/parquet_utils.py
cdd_gae/tests/__init__.py
cdd_gae/tests/test_cli.py
cdd_gae/tests/test_ndb_parse.py
cdd_gae/tests/test_parquet_to_table.py
cdd_gae/tests/test_parse_parquet.py
cdd_gae/tests/test_parse_parquet_utils.py
cdd_gae/tests/test_setup.py
cdd_gae/tests/test_webapp2_to_fastapi.py
cdd_gae/tests/test_webapp2_to_fastapi_utils.py
cdd_gae/tests/mocks/__init__.py
cdd_gae/tests/mocks/fastapi.py
cdd_gae/tests/mocks/ndb.py
cdd_gae/tests/mocks/webapp2.py
python_cdd_gae-0.0.15.dist-info/LICENSE-APACHE
python_cdd_gae-0.0.15.dist-info/LICENSE-MIT
python_cdd_gae-0.0.15.dist-info/METADATA
python_cdd_gae-0.0.15.dist-info/WHEEL
python_cdd_gae-0.0.15.dist-info/top_level.txt
python_cdd_gae-0.0.15.dist-info/RECORD
